mono/__init__.py
mono/ansi.py
mono/shells/__init__.py
mono/shells/bash.py
mono/shells/cmd.py
mono/shells/default.py
mono/shells/powershell.py
mono/shells/python.py
mono/styles.py
mono/tab.py
mono/tabs.py
mono/terminal.py
mono/text.py
mono/theme.py
mono/utils/__init__.py
mono/utils/scrollbar.py
mono_term-0.36.0.dist-info/LICENSE
mono_term-0.36.0.dist-info/METADATA
mono_term-0.36.0.dist-info/WHEEL
mono_term-0.36.0.dist-info/RECORD
