Metadata-Version: 2.1
Name: mono-term
Version: 0.36.0
Summary: Embeddable terminal emulator
License: MIT
Author: Billy
Author-email: billydevbusiness@gmail.com
Requires-Python: >=3.10,<4.0
Classifier: License :: OSI Approved :: MIT License
Classifier: Programming Language :: Python :: 3
Classifier: Programming Language :: Python :: 3.10
Classifier: Programming Language :: Python :: 3.11
Classifier: Programming Language :: Python :: 3.12
Requires-Dist: ptyprocess (>=0.7.0,<0.8.0) ; sys_platform == "linux"
Requires-Dist: pywinpty (>=2.0.13,<3.0.0) ; sys_platform == "win32"
